{"title":"UjNotes","xurl":"1","async":"0","date":"2016 Jul 03","desc":"Ujjwal Singh's notes","content":"<div class=\"content\">\r\n\t<div class='message'>select one:<\/div>\r\n\t<div class=\"center\">\r\n\t\t<div class=\"sidebar-nav-group\">\r\n\t\t\t<a class=\"XURL_ sidebar-nav-norm sidebar-nav-l-1\" id=\"os\" href=\"\/os\" target=\"_blank\" onclick='trackOutboundLink(\"OS\",\"https:\/\/drive.google.com\/folderview?id=0B0pxLafSqCjKQ0tXc281bnJoaTQ\"); return false;'>\r\n\t\t\t\t<span>OS<\/span>\r\n\t\t\t<\/a><a class=\"XURL_ sidebar-nav-norm sidebar-nav-l-1\" id=\"program\" href=\"\/program\" target=\"_blank\" onclick='trackOutboundLink(\"Program\",\"https:\/\/drive.google.com\/folderview?id=0B0pxLafSqCjKZkdRZk5ac2p4Zlk\"); return false;'>\r\n\t\t\t\t<span>Program<\/span>\r\n\t\t\t<\/a><a class=\"XURL_ sidebar-nav-norm sidebar-nav-l-1\" id=\"programming\" href=\"\/programming\" target=\"_blank\" onclick='trackOutboundLink(\"Programming\",\"https:\/\/drive.google.com\/folderview?id=0B0pxLafSqCjKT244VW92b1pGVnM\"); return false;'>\r\n\t\t\t\t<span>Programming<\/span>\r\n\t\t\t<\/a>\r\n\t\t<\/div>\r\n\t<\/div>\r\n<\/div>\r\n"}